[
    {
    "id": "blog_1",
    "title":"Un título para el blog",
    "day":"26",
    "month":"Febrero",
    "year":"1899",
    "author":"Admin",
    "description":"Esta es una pequeña descripción de lo que trata este blog"
    },
    {
    "id": "blog_2",
    "title":"Un título para el blog",
    "day":"26",
    "month":"Febrero",
    "year":"1899",
    "author":"Admin",
    "description":"Esta es una pequeña descripción de lo que trata este blog"
    },
    {
    "id": "blog_3",
    "title":"Un título para el blog",
    "day":"26",
    "month":"Febrero",
    "year":"1899",
    "author":"Admin",
    "description":"Esta es una pequeña descripción de lo que trata este blog"
    },
    {
    "id": "blog_4",
    "title":"Un título para el blog",
    "day":"26",
    "month":"Febrero",
    "year":"1899",
    "author":"Admin",
    "description":"Esta es una pequeña descripción de lo que trata este blog"
    },
    {
    "id": "blog_5",
    "title":"Un título para el blog",
    "day":"26",
    "month":"Febrero",
    "year":"1899",
    "author":"Admin",
    "description":"Esta es una pequeña descripción de lo que trata este blog"
    },
    {
    "id": "blog_6",
    "title":"Un título para el blog",
    "day":"26",
    "month":"Febrero",
    "year":"1899",
    "author":"Admin",
    "description":"Esta es una pequeña descripción de lo que trata este blog"
    }
]